timeserver.py
schleetime-1.0.0.dist-info/METADATA
schleetime-1.0.0.dist-info/WHEEL
schleetime-1.0.0.dist-info/entry_points.txt
schleetime-1.0.0.dist-info/top_level.txt
schleetime-1.0.0.dist-info/RECORD
