Metadata-Version: 2.1
Name: schleetime
Version: 1.0.0
Author: Gabe Schlee
Author-email: schleeg@canisius.edu
Requires-Python: >=3.8
Requires-Dist: flask >=2.0.0
